ocrlayout/__init__.py
ocrlayout/bboxconfig.py
ocrlayout/bboxhelper.py
ocrlayout/bboxlog.py
ocrlayout/bboxutils.py
ocrlayout/config/annotations.json
ocrlayout/config/config.json
ocrlayout/config/logging.conf
ocrlayout-0.9.dist-info/LICENSE
ocrlayout-0.9.dist-info/METADATA
ocrlayout-0.9.dist-info/WHEEL
ocrlayout-0.9.dist-info/top_level.txt
ocrlayout-0.9.dist-info/RECORD
