Metadata-Version: 2.1
Name: ocrlayout
Version: 0.9
Summary: A Helper class to get more meaninful text out of common OCR outputs
Home-page: https://puthurr.github.io/
Author: Nicolas Uthurriague
Author-email: puthurr@hotmail.com
License: MIT
Project-URL: Documentation, https://puthurr.github.io/
Project-URL: Source, https://github.com/puthurr/ocrlayout/
Project-URL: Tracker, https://github.com/puthurr/ocrlayout/issues
Project-URL: Recipes, https://github.com/puthurr/ocrlayout-recipes
Keywords: OCR,Computer Vision,Text Extraction,Knowledge Mining,BoundingBoxes
Platform: UNKNOWN
Classifier: Programming Language :: Python :: 3.8
Classifier: License :: OSI Approved :: MIT License
Classifier: Operating System :: OS Independent
Requires-Python: >=3.8
Requires-Dist: numpy
